hapm/__init__.py
hapm/repository.py
hapm/cli/__init__.py
hapm/cli/common.py
hapm/cli/export.py
hapm/cli/install.py
hapm/cli/versions.py
hapm/color/__init__.py
hapm/color/constants.py
hapm/color/ink.py
hapm/git/__init__.py
hapm/git/file.py
hapm/git/path.py
hapm/git/tarball.py
hapm/git/versions.py
hapm/integration/__init__.py
hapm/integration/package.py
hapm/manager/__init__.py
hapm/manager/diff.py
hapm/manager/lockfile.py
hapm/manifest/__init__.py
hapm/manifest/category.py
hapm/manifest/location.py
hapm/manifest/manifest.py
hapm/package/__init__.py
hapm/package/base.py
hapm/package/description.py
hapm/plugin/__init__.py
hapm/plugin/package.py
hapm/report/__init__.py
hapm/report/diff.py
hapm/report/errors.py
hapm/report/lists.py
hapm/report/progress.py
hapm/report/summary.py
hapm/report/utils.py
hapm/version/__init__.py
hapm/version/find.py
hapm/version/parse.py
hapm/version/version.py
hapm-0.3.0.dist-info/._PKG-INFO
hapm-0.3.0.dist-info/._SOURCES.txt
hapm-0.3.0.dist-info/._dependency_links.txt
hapm-0.3.0.dist-info/._entry_points.txt
hapm-0.3.0.dist-info/._requires.txt
hapm-0.3.0.dist-info/._top_level.txt
hapm-0.3.0.dist-info/LICENSE
hapm-0.3.0.dist-info/METADATA
hapm-0.3.0.dist-info/WHEEL
hapm-0.3.0.dist-info/entry_points.txt
hapm-0.3.0.dist-info/top_level.txt
hapm-0.3.0.dist-info/RECORD
