Metadata-Version: 2.2
Name: hapm
Version: 0.3.0
Summary: Home Assistant package management applications
Author-email: Mikhael Khrustik <misha@myrt.co>
License: MIT
Keywords: cli,home-assistant,package-manager
Classifier: Programming Language :: Python :: 3
Classifier: License :: OSI Approved :: MIT License
Requires-Python: >=3.12
License-File: LICENSE
Requires-Dist: ruamel.yaml>=0.18.1
Requires-Dist: arrrgs>=3.0.0
Requires-Dist: PyGithub>=2.5.0
Requires-Dist: gitpython>=3.1.44
Requires-Dist: requests>=2.32.3
Requires-Dist: urllib3>=2.3.0
